CONTRIBUTORS
LICENSE
README.md
example.pdf
example.tex
py-and-sty.dtx
remote-sagetex.dtx
sagetex-extract
sagetex-makestatic
sagetex-remote
sagetex-run
sagetex.dtx
sagetex.ins
sagetex.pdf
sagetex.py
sagetex.sty
sagetexparse.py
scripts.dtx
setup.py
sagetex.egg-info/PKG-INFO
sagetex.egg-info/SOURCES.txt
sagetex.egg-info/dependency_links.txt
sagetex.egg-info/requires.txt
sagetex.egg-info/top_level.txt